kbdextension.py
kbdextension-1.0.1.dist-info/LICENSE.md
kbdextension-1.0.1.dist-info/METADATA
kbdextension-1.0.1.dist-info/WHEEL
kbdextension-1.0.1.dist-info/top_level.txt
kbdextension-1.0.1.dist-info/RECORD
