Metadata-Version: 2.1
Name: kbdextension
Version: 1.0.1
Summary: Extension for python-markdown that adds markdown syntax for the KBD HTML tag.
Home-page: https://github.com/RickTalken/kbdextension.git
Author: Rick Talken
Author-email: rick@talken.com
License: MIT
Platform: UNKNOWN
Classifier: License :: OSI Approved :: MIT License
Classifier: Programming Language :: Python :: 3
Classifier: Operating System :: OS Independent
Classifier: Intended Audience :: Developers
Classifier: Topic :: Text Processing :: Markup
Classifier: Topic :: Text Processing :: Markup :: HTML
Requires-Dist: markdown (>=3.0)
